comfyui_frontend_package/__init__.py
comfyui_frontend_package/static/index.html
comfyui_frontend_package/static/materialdesignicons.min.css
comfyui_frontend_package/static/user.css
comfyui_frontend_package/static/assets/AboutPanel-DdDhHGYm.js
comfyui_frontend_package/static/assets/AboutPanel-DdDhHGYm.js.map
comfyui_frontend_package/static/assets/BaseViewTemplate-Dccv09E9.js
comfyui_frontend_package/static/assets/BaseViewTemplate-Dccv09E9.js.map
comfyui_frontend_package/static/assets/CREDIT.txt
comfyui_frontend_package/static/assets/CreditsPanel-XszJL1ia.js
comfyui_frontend_package/static/assets/CreditsPanel-XszJL1ia.js.map
comfyui_frontend_package/static/assets/DesktopStartView-Cu24wK2n.js
comfyui_frontend_package/static/assets/DesktopStartView-Cu24wK2n.js.map
comfyui_frontend_package/static/assets/DesktopUpdateView-CoZUcBzh.css
comfyui_frontend_package/static/assets/DesktopUpdateView-uiA7ZFbh.js
comfyui_frontend_package/static/assets/DesktopUpdateView-uiA7ZFbh.js.map
comfyui_frontend_package/static/assets/DownloadGitView-DTu6U1R8.js
comfyui_frontend_package/static/assets/DownloadGitView-DTu6U1R8.js.map
comfyui_frontend_package/static/assets/ExtensionPanel-DuiRfYmE.js
comfyui_frontend_package/static/assets/ExtensionPanel-DuiRfYmE.js.map
comfyui_frontend_package/static/assets/GraphView-DrZzF0SR.js
comfyui_frontend_package/static/assets/GraphView-DrZzF0SR.js.map
comfyui_frontend_package/static/assets/GraphView-zz4tz6fy.css
comfyui_frontend_package/static/assets/InstallView-CjZwWmyC.js
comfyui_frontend_package/static/assets/InstallView-CjZwWmyC.js.map
comfyui_frontend_package/static/assets/InstallView-D0Upzwxf.css
comfyui_frontend_package/static/assets/KeybindingPanel-5SFEBgOD.js
comfyui_frontend_package/static/assets/KeybindingPanel-5SFEBgOD.js.map
comfyui_frontend_package/static/assets/KeybindingPanel-tsP0vxL-.css
comfyui_frontend_package/static/assets/MaintenanceView-CvMvGk8j.js
comfyui_frontend_package/static/assets/MaintenanceView-CvMvGk8j.js.map
fs_comfyui_frontend_package-1.20.2.dist-info/METADATA
fs_comfyui_frontend_package-1.20.2.dist-info/WHEEL
fs_comfyui_frontend_package-1.20.2.dist-info/top_level.txt
fs_comfyui_frontend_package-1.20.2.dist-info/RECORD
