Metadata-Version: 2.4
Name: fs_comfyui_frontend_package
Version: 1.20.2
Summary: ComfyUI Frontend Package for web interface
Classifier: Programming Language :: Python :: 3
Classifier: License :: OSI Approved :: MIT License
Classifier: Operating System :: OS Independent
Requires-Python: >=3.9
Dynamic: classifier
Dynamic: description
Dynamic: description-content-type
Dynamic: requires-python
Dynamic: summary
